uq_metrics/__init__.py
uq_metrics/_plots.py
uq_metrics/_utils.py
uq_metrics/metrics.py
uq_metrics-0.1.0.dist-info/METADATA
uq_metrics-0.1.0.dist-info/WHEEL
uq_metrics-0.1.0.dist-info/licenses/LICENSE
uq_metrics-0.1.0.dist-info/RECORD
