Metadata-Version: 2.4
Name: uq-metrics
Version: 0.1.0
Summary: Uncertainty quantification metrics for model evaluation
Project-URL: Homepage, https://github.com/debargha/uq-metrics
Author: Debargha
License-Expression: MIT
License-File: LICENSE
Keywords: calibration,machine-learning,metrics,quantification,uncertainty
Classifier: Development Status :: 4 - Beta
Classifier: Intended Audience :: Developers
Classifier: Intended Audience :: Science/Research
Classifier: License :: OSI Approved :: MIT License
Classifier: Programming Language :: Python :: 3
Classifier: Programming Language :: Python :: 3.8
Classifier: Programming Language :: Python :: 3.9
Classifier: Programming Language :: Python :: 3.10
Classifier: Programming Language :: Python :: 3.11
Classifier: Programming Language :: Python :: 3.12
Classifier: Topic :: Scientific/Engineering
Requires-Python: >=3.8
Requires-Dist: numpy>=1.20
Provides-Extra: plot
Requires-Dist: matplotlib>=3.0; extra == 'plot'
